rectified_flow/__init__.py
rectified_flow/rectified_flow.py
rectified_flow/utils.py
rectified_flow/flow_components/__init__.py
rectified_flow/flow_components/interpolation_solver.py
rectified_flow/flow_components/loss_function.py
rectified_flow/flow_components/train_time_sampler.py
rectified_flow/flow_components/train_time_weight.py
rectified_flow/metrics/__init__.py
rectified_flow/metrics/clip_score.py
rectified_flow/models/__init__.py
rectified_flow/models/dit.py
rectified_flow/models/flux_dev.py
rectified_flow/models/gauss_analytic.py
rectified_flow/models/toy_mlp.py
rectified_flow/models/unet.py
rectified_flow/samplers/__init__.py
rectified_flow/samplers/base_sampler.py
rectified_flow/samplers/curved_euler_sampler.py
rectified_flow/samplers/euler_sampler.py
rectified_flow/samplers/noise_refresh_sampler.py
rectified_flow/samplers/overshooting_sampler.py
rectified_flow/samplers/sde_sampler.py
rectified_flow/samplers/stochastic_curved_euler_sampler.py
rectified_flow-1.0.1.dist-info/LICENSE
rectified_flow-1.0.1.dist-info/METADATA
rectified_flow-1.0.1.dist-info/WHEEL
rectified_flow-1.0.1.dist-info/top_level.txt
rectified_flow-1.0.1.dist-info/RECORD
