Metadata-Version: 2.1
Name: rectified-flow
Version: 1.0.1
Summary: A PyTorch implementation of Rectified Flow and its variants.
Home-page: https://github.com/lqiang67/rectified-flow
Author: Qiang Liu, Runlong Liao, Bo Liu, Xixi Hu
Author-email: rectifiedflow@gmail.com
Keywords: pytorch,rectified-flow,generative-modeling
Classifier: Programming Language :: Python :: 3
Classifier: License :: OSI Approved :: MIT License
Classifier: Operating System :: OS Independent
Requires-Python: >=3.10
License-File: LICENSE
Requires-Dist: accelerate>=1.2.0
Requires-Dist: openai-clip==1.0.1
Requires-Dist: diffusers>=0.31.0
Requires-Dist: matplotlib>=3.9.3
Requires-Dist: numpy
Requires-Dist: packaging
Requires-Dist: Pillow
Requires-Dist: plotly
Requires-Dist: scikit_learn
Requires-Dist: scipy
Requires-Dist: sympy
Requires-Dist: timm>=1.0.12
Requires-Dist: torch>=2.5.0
Requires-Dist: torchvision>=0.20.0
Requires-Dist: tqdm
